ansys/mechanical/core/__init__.py
ansys/mechanical/core/_version.py
ansys/mechanical/core/embedding/__init__.py
ansys/mechanical/core/embedding/addins.py
ansys/mechanical/core/embedding/app.py
ansys/mechanical/core/embedding/app_libraries.py
ansys/mechanical/core/embedding/appdata.py
ansys/mechanical/core/embedding/background.py
ansys/mechanical/core/embedding/cleanup_gui.py
ansys/mechanical/core/embedding/enum_importer.py
ansys/mechanical/core/embedding/find_mechanical.py
ansys/mechanical/core/embedding/global_importer.py
ansys/mechanical/core/embedding/graphics/__init__.py
ansys/mechanical/core/embedding/graphics/embedding_plotter.py
ansys/mechanical/core/embedding/graphics/usd_converter.py
ansys/mechanical/core/embedding/graphics/utils.py
ansys/mechanical/core/embedding/imports.py
ansys/mechanical/core/embedding/initializer.py
ansys/mechanical/core/embedding/ipython_shell.py
ansys/mechanical/core/embedding/license_manager.py
ansys/mechanical/core/embedding/loader.py
ansys/mechanical/core/embedding/logger/__init__.py
ansys/mechanical/core/embedding/logger/environ.py
ansys/mechanical/core/embedding/logger/linux_api.py
ansys/mechanical/core/embedding/logger/sinks.py
ansys/mechanical/core/embedding/logger/windows_api.py
ansys/mechanical/core/embedding/mechanical_warnings.py
ansys/mechanical/core/embedding/messages.py
ansys/mechanical/core/embedding/poster.py
ansys/mechanical/core/embedding/resolver.py
ansys/mechanical/core/embedding/rpc/__init__.py
ansys/mechanical/core/embedding/rpc/client.py
ansys/mechanical/core/embedding/rpc/default_server.py
ansys/mechanical/core/embedding/rpc/server.py
ansys/mechanical/core/embedding/rpc/utils.py
ansys/mechanical/core/embedding/runtime.py
ansys/mechanical/core/embedding/shell.py
ansys/mechanical/core/embedding/shims.py
ansys/mechanical/core/embedding/transaction.py
ansys/mechanical/core/embedding/ui.py
ansys/mechanical/core/embedding/utils.py
ansys/mechanical/core/errors.py
ansys/mechanical/core/examples/__init__.py
ansys_mechanical_core-0.12.2.dist-info/METADATA
ansys_mechanical_core-0.12.2.dist-info/WHEEL
ansys_mechanical_core-0.12.2.dist-info/entry_points.txt
ansys_mechanical_core-0.12.2.dist-info/licenses/LICENSE
ansys_mechanical_core-0.12.2.dist-info/RECORD
