Metadata-Version: 2.1
Name: ansys-mechanical-core
Version: 0.12.2
Summary: A python wrapper for Ansys Mechanical
Keywords: pymechanical,mechanical,ansys,pyansys
Author-Email: "ANSYS, Inc." <pyansys.core@ansys.com>
Maintainer-Email: "ANSYS, Inc." <pyansys.core@ansys.com>
License: MIT License
Classifier: Development Status :: 4 - Beta
Classifier: Intended Audience :: Science/Research
Classifier: Topic :: Scientific/Engineering :: Information Analysis
Classifier: Programming Language :: Python :: 3.10
Classifier: Programming Language :: Python :: 3.11
Classifier: Programming Language :: Python :: 3.12
Classifier: Programming Language :: Python :: 3.13
Classifier: License :: OSI Approved :: MIT License
Classifier: Operating System :: OS Independent
Project-URL: Homepage, https://github.com/ansys/pymechanical
Project-URL: Documentation, https://mechanical.docs.pyansys.com
Project-URL: Repository, https://github.com/ansys/pymechanical
Project-URL: Issues, https://github.com/ansys/pymechanical/issues
Project-URL: Changelog, https://mechanical.docs.pyansys.com/version/stable/changelog.html
Requires-Python: <4.0,>=3.10
Requires-Dist: ansys-api-mechanical==0.1.3
Requires-Dist: ansys-mechanical-stubs==0.1.9
Requires-Dist: ansys-pythonnet>=3.1.0rc6
Requires-Dist: ansys-tools-common>=0.4.0
Requires-Dist: appdirs>=1.4.0
Requires-Dist: click>=8.1.3
Requires-Dist: clr-loader>=0.2.6
Requires-Dist: grpcio>=1.30.0
Requires-Dist: protobuf<7,>=3.12.2
Requires-Dist: psutil>=6
Requires-Dist: tqdm>=4.45.0
Requires-Dist: requests<3,>=2
Provides-Extra: tests
Requires-Dist: pytest==9.0.2; extra == "tests"
Requires-Dist: pytest-cov==7.0.0; extra == "tests"
Requires-Dist: pytest-print==1.2.0; extra == "tests"
Requires-Dist: psutil==7.2.1; extra == "tests"
Provides-Extra: doc
Requires-Dist: sphinx==8.2.3; extra == "doc"
Requires-Dist: ansys-sphinx-theme[autoapi,changelog]==1.6.4; extra == "doc"
Requires-Dist: imageio-ffmpeg==0.6.0; extra == "doc"
Requires-Dist: imageio==2.37.2; extra == "doc"
Requires-Dist: jupyter_sphinx==0.5.3; extra == "doc"
Requires-Dist: jupyterlab>=3.2.8; extra == "doc"
Requires-Dist: matplotlib==3.10.8; extra == "doc"
Requires-Dist: numpy==2.2.6; extra == "doc"
Requires-Dist: numpydoc==1.8.0; extra == "doc"
Requires-Dist: pypandoc==1.16.2; extra == "doc"
Requires-Dist: sphinx-autobuild==2025.8.25; extra == "doc"
Requires-Dist: sphinx-autodoc-typehints==3.1.0; extra == "doc"
Requires-Dist: sphinx-copybutton==0.5.2; extra == "doc"
Requires-Dist: sphinx_design==0.6.1; extra == "doc"
Requires-Dist: sphinx-gallery==0.20.0; extra == "doc"
Requires-Dist: sphinx-notfound-page==1.1.0; extra == "doc"
Requires-Dist: sphinxcontrib-websupport==2.0.0; extra == "doc"
Requires-Dist: sphinx-click==6.2.0; extra == "doc"
Requires-Dist: ansys-tools-visualization-interface>=0.2.6; extra == "doc"
Provides-Extra: graphics
Requires-Dist: ansys-tools-visualization-interface>=0.2.6; extra == "graphics"
Requires-Dist: usd-core==25.11; extra == "graphics"
Provides-Extra: rpc
Requires-Dist: rpyc==6.0.2; extra == "rpc"
Requires-Dist: toolz==1.1.0; extra == "rpc"
Provides-Extra: pim
Requires-Dist: ansys-platform-instancemanagement>=1.0.1; extra == "pim"
